[{"code":"4160952","prefecture_code":22,"city":"富士市","town":"青葉町"},{"code":"4160901","prefecture_code":22,"city":"富士市","town":"岩本"},{"code":"4160912","prefecture_code":22,"city":"富士市","town":"加島町"},{"code":"4160942","prefecture_code":22,"city":"富士市","town":"上横割"},{"code":"4160939","prefecture_code":22,"city":"富士市","town":"川成島"},{"code":"4160955","prefecture_code":22,"city":"富士市","town":"川成新町"},{"code":"4160946","prefecture_code":22,"city":"富士市","town":"五貫島"},{"code":"4160905","prefecture_code":22,"city":"富士市","town":"五味島"},{"code":"4160934","prefecture_code":22,"city":"富士市","town":"鮫島"},{"code":"4160943","prefecture_code":22,"city":"富士市","town":"下横割"},{"code":"4160941","prefecture_code":22,"city":"富士市","town":"十兵衛"},{"code":"4160935","prefecture_code":22,"city":"富士市","town":"田子"},{"code":"4160931","prefecture_code":22,"city":"富士市","town":"蓼原"},{"code":"4160953","prefecture_code":22,"city":"富士市","town":"蓼原町"},{"code":"4160936","prefecture_code":22,"city":"富士市","town":"中河原"},{"code":"4160907","prefecture_code":22,"city":"富士市","town":"中島"},{"code":"4160933","prefecture_code":22,"city":"富士市","town":"中丸"},{"code":"4160902","prefecture_code":22,"city":"富士市","town":"長通"},{"code":"4160911","prefecture_code":22,"city":"富士市","town":"八幡町"},{"code":"4160938","prefecture_code":22,"city":"富士市","town":"浜田町"},{"code":"4160915","prefecture_code":22,"city":"富士市","town":"富士町"},{"code":"4160916","prefecture_code":22,"city":"富士市","town":"平垣"},{"code":"4160918","prefecture_code":22,"city":"富士市","town":"平垣町"},{"code":"4160913","prefecture_code":22,"city":"富士市","town":"平垣本町"},{"code":"4160914","prefecture_code":22,"city":"富士市","town":"本町"},{"code":"4160937","prefecture_code":22,"city":"富士市","town":"前田"},{"code":"4160909","prefecture_code":22,"city":"富士市","town":"松岡"},{"code":"4160919","prefecture_code":22,"city":"富士市","town":"松富町"},{"code":"4160903","prefecture_code":22,"city":"富士市","town":"松本"},{"code":"4160921","prefecture_code":22,"city":"富士市","town":"水戸島"},{"code":"4160924","prefecture_code":22,"city":"富士市","town":"水戸島本町"},{"code":"4160922","prefecture_code":22,"city":"富士市","town":"水戸島元町"},{"code":"4160947","prefecture_code":22,"city":"富士市","town":"宮下"},{"code":"4160945","prefecture_code":22,"city":"富士市","town":"宮島"},{"code":"4160906","prefecture_code":22,"city":"富士市","town":"本市場"},{"code":"4160904","prefecture_code":22,"city":"富士市","town":"本市場新田"},{"code":"4160954","prefecture_code":22,"city":"富士市","town":"本市場町"},{"code":"4160917","prefecture_code":22,"city":"富士市","town":"元町"},{"code":"4160949","prefecture_code":22,"city":"富士市","town":"森下"},{"code":"4160948","prefecture_code":22,"city":"富士市","town":"森島"},{"code":"4160932","prefecture_code":22,"city":"富士市","town":"柳島"},{"code":"4160908","prefecture_code":22,"city":"富士市","town":"柚木"},{"code":"4160944","prefecture_code":22,"city":"富士市","town":"横割"},{"code":"4160923","prefecture_code":22,"city":"富士市","town":"横割本町"},{"code":"4160951","prefecture_code":22,"city":"富士市","town":"米之宮町"}]