[{"code":"5840000","prefecture_code":27,"city":"富田林市","town":""},{"code":"5840076","prefecture_code":27,"city":"富田林市","town":"青葉丘"},{"code":"5840006","prefecture_code":27,"city":"富田林市","town":"旭ケ丘町"},{"code":"5840012","prefecture_code":27,"city":"富田林市","town":"粟ケ池町"},{"code":"5840001","prefecture_code":27,"city":"富田林市","town":"梅の里"},{"code":"5840056","prefecture_code":27,"city":"富田林市","town":"嬉"},{"code":"5840095","prefecture_code":27,"city":"富田林市","town":"毛人谷"},{"code":"5840058","prefecture_code":27,"city":"富田林市","town":"彼方"},{"code":"5840040","prefecture_code":27,"city":"富田林市","town":"かがり台"},{"code":"5840078","prefecture_code":27,"city":"富田林市","town":"加太"},{"code":"5840014","prefecture_code":27,"city":"富田林市","town":"川面町"},{"code":"5840049","prefecture_code":27,"city":"富田林市","town":"川向町"},{"code":"5840054","prefecture_code":27,"city":"富田林市","town":"甘南備"},{"code":"5840008","prefecture_code":27,"city":"富田林市","town":"喜志"},{"code":"5840003","prefecture_code":27,"city":"富田林市","town":"喜志新家町"},{"code":"5840005","prefecture_code":27,"city":"富田林市","town":"喜志町"},{"code":"5840042","prefecture_code":27,"city":"富田林市","town":"北大伴町"},{"code":"5840004","prefecture_code":27,"city":"富田林市","town":"木戸山町"},{"code":"5840041","prefecture_code":27,"city":"富田林市","town":"楠町"},{"code":"5840074","prefecture_code":27,"city":"富田林市","town":"久野喜台"},{"code":"5840036","prefecture_code":27,"city":"富田林市","town":"甲田"},{"code":"5840082","prefecture_code":27,"city":"富田林市","town":"向陽台"},{"code":"5840083","prefecture_code":27,"city":"富田林市","town":"小金台"},{"code":"5840079","prefecture_code":27,"city":"富田林市","town":"五軒家"},{"code":"5840031","prefecture_code":27,"city":"富田林市","town":"寿町"},{"code":"5840070","prefecture_code":27,"city":"富田林市","town":"金剛錦織台"},{"code":"5840065","prefecture_code":27,"city":"富田林市","town":"金剛伏山台"},{"code":"5840015","prefecture_code":27,"city":"富田林市","town":"西条町"},{"code":"5840013","prefecture_code":27,"city":"富田林市","town":"桜井町"},{"code":"5840084","prefecture_code":27,"city":"富田林市","town":"桜ケ丘町"},{"code":"5840052","prefecture_code":27,"city":"富田林市","town":"佐備"},{"code":"5840034","prefecture_code":27,"city":"富田林市","town":"清水町"},{"code":"5840092","prefecture_code":27,"city":"富田林市","town":"昭和町"},{"code":"5840077","prefecture_code":27,"city":"富田林市","town":"新青葉丘町"},{"code":"5840085","prefecture_code":27,"city":"富田林市","town":"新家"},{"code":"5840091","prefecture_code":27,"city":"富田林市","town":"新堂"},{"code":"5840062","prefecture_code":27,"city":"富田林市","town":"須賀"},{"code":"5840072","prefecture_code":27,"city":"富田林市","town":"高辺台"},{"code":"5840035","prefecture_code":27,"city":"富田林市","town":"谷川町"},{"code":"5840016","prefecture_code":27,"city":"富田林市","town":"通法寺町"},{"code":"5840081","prefecture_code":27,"city":"富田林市","town":"廿山"},{"code":"5840086","prefecture_code":27,"city":"富田林市","town":"津々山台"},{"code":"5840073","prefecture_code":27,"city":"富田林市","town":"寺池台"},{"code":"5840032","prefecture_code":27,"city":"富田林市","town":"常盤町"},{"code":"5840033","prefecture_code":27,"city":"富田林市","town":"富田林町"},{"code":"5840027","prefecture_code":27,"city":"富田林市","town":"中野"},{"code":"5840021","prefecture_code":27,"city":"富田林市","town":"中野町"},{"code":"5840022","prefecture_code":27,"city":"富田林市","town":"中野町東"},{"code":"5840028","prefecture_code":27,"city":"富田林市","town":"中野町西"},{"code":"5840051","prefecture_code":27,"city":"富田林市","town":"楠風台"},{"code":"5840048","prefecture_code":27,"city":"富田林市","town":"西板持町"},{"code":"5840063","prefecture_code":27,"city":"富田林市","town":"錦織"},{"code":"5840066","prefecture_code":27,"city":"富田林市","town":"錦織北"},{"code":"5840068","prefecture_code":27,"city":"富田林市","town":"錦織中"},{"code":"5840069","prefecture_code":27,"city":"富田林市","town":"錦織東"},{"code":"5840067","prefecture_code":27,"city":"富田林市","town":"錦織南"},{"code":"5840038","prefecture_code":27,"city":"富田林市","town":"錦ケ丘町"},{"code":"5840046","prefecture_code":27,"city":"富田林市","town":"東板持町"},{"code":"5840002","prefecture_code":27,"city":"富田林市","town":"平町"},{"code":"5840055","prefecture_code":27,"city":"富田林市","town":"伏見堂"},{"code":"5840061","prefecture_code":27,"city":"富田林市","town":"伏山"},{"code":"5840071","prefecture_code":27,"city":"富田林市","town":"藤沢台"},{"code":"5840064","prefecture_code":27,"city":"富田林市","town":"不動ケ丘町"},{"code":"5840094","prefecture_code":27,"city":"富田林市","town":"富美ケ丘町"},{"code":"5840044","prefecture_code":27,"city":"富田林市","town":"別井"},{"code":"5840093","prefecture_code":27,"city":"富田林市","town":"本町"},{"code":"5840026","prefecture_code":27,"city":"富田林市","town":"緑ケ丘町"},{"code":"5840007","prefecture_code":27,"city":"富田林市","town":"南旭ケ丘町"},{"code":"5840043","prefecture_code":27,"city":"富田林市","town":"南大伴町"},{"code":"5840037","prefecture_code":27,"city":"富田林市","town":"宮甲田町"},{"code":"5840011","prefecture_code":27,"city":"富田林市","town":"宮町"},{"code":"5840039","prefecture_code":27,"city":"富田林市","town":"美山台"},{"code":"5840045","prefecture_code":27,"city":"富田林市","town":"山中田町"},{"code":"5840047","prefecture_code":27,"city":"富田林市","town":"山手町"},{"code":"5840057","prefecture_code":27,"city":"富田林市","town":"横山"},{"code":"5840053","prefecture_code":27,"city":"富田林市","town":"龍泉"},{"code":"5840024","prefecture_code":27,"city":"富田林市","town":"若松町"},{"code":"5840023","prefecture_code":27,"city":"富田林市","town":"若松町東"},{"code":"5840025","prefecture_code":27,"city":"富田林市","town":"若松町西"}]